md2confluence.py
md2confluence-1.1.0.dist-info/licenses/LICENSE
md2confluence-1.1.0.dist-info/METADATA
md2confluence-1.1.0.dist-info/WHEEL
md2confluence-1.1.0.dist-info/entry_points.txt
md2confluence-1.1.0.dist-info/top_level.txt
md2confluence-1.1.0.dist-info/RECORD
