Metadata-Version: 2.4
Name: md2confluence
Version: 1.1.0
Summary: Sync Markdown documentation to Confluence Cloud
License: MIT
Project-URL: Repository, https://pypi.org/project/md2confluence/
Requires-Python: >=3.9
License-File: LICENSE
Requires-Dist: requests>=2.32.0
Dynamic: license-file
